discoin/__init__.py
discoin/classes.py
discoin/client.py
discoin/config.py
discoin/errors.py
discoin/utils.py
discoin-4.0.dist-info/LICENSE
discoin-4.0.dist-info/METADATA
discoin-4.0.dist-info/WHEEL
discoin-4.0.dist-info/top_level.txt
discoin-4.0.dist-info/RECORD
