Metadata-Version: 2.1
Name: discoin
Version: 4.0
Summary: Official Discoin Package
Home-page: https://github.com/Discoin/discoin.py
Author: Dr_Ari_Gami
Author-email: drarigami@gmail.com
License: UNKNOWN
Platform: UNKNOWN
Classifier: Programming Language :: Python :: 3
Classifier: License :: OSI Approved :: MIT License
Classifier: Operating System :: OS Independent
Requires-Python: >=3.6
